{
  "temperature": 0.2,
  "downfall": 0.4,
  "precipitation": "none",
  "effects": {
    "sky_color": 6652120,
    "fog_color": 9540292,
    "water_color": 1737654,
    "water_fog_color": 1737654,
    "grass_color": 416541,
    "foliage_color": 2129468
  },
  "spawners": {},
  "spawn_costs": {},
  "carvers": {},
  "features": [
    [
      "hades:spike",
      "hades:elysium_grass_patch"
    ],
    [
      "hades:populus_trees_rare"
    ],
    [
      "hades:elysium_bush",
      "hades:elysium_rock"
    ]
  ]
}
